cross_docs/__init__.py
cross_docs/cli.py
cross_docs/config.py
cross_docs/markdown.py
cross_docs/middleware.py
cross_docs/navigation.py
cross_docs/routes.py
cross_docs/api/__init__.py
cross_docs/api/base.py
cross_docs/api/registry.py
cross_docs/api/plugins/__init__.py
cross_docs/api/plugins/python.py
cross_docs-0.12.0.dist-info/METADATA
cross_docs-0.12.0.dist-info/WHEEL
cross_docs-0.12.0.dist-info/entry_points.txt
cross_docs-0.12.0.dist-info/RECORD
