Metadata-Version: 2.4
Name: cross-docs
Version: 0.12.0
Summary: Documentation framework built on Cross-Inertia
Project-URL: Homepage, https://github.com/usecross/cross-docs
Project-URL: Documentation, https://cross-docs.dev
Project-URL: Repository, https://github.com/usecross/cross-docs
Author-email: Patrick Arminio <patrick.arminio@gmail.com>
License: MIT
Keywords: documentation,fastapi,inertia,react,ssr
Classifier: Development Status :: 3 - Alpha
Classifier: Framework :: FastAPI
Classifier: Intended Audience :: Developers
Classifier: License :: OSI Approved :: MIT License
Classifier: Programming Language :: Python :: 3
Classifier: Programming Language :: Python :: 3.10
Classifier: Programming Language :: Python :: 3.11
Classifier: Programming Language :: Python :: 3.12
Classifier: Programming Language :: Python :: 3.13
Classifier: Topic :: Documentation
Classifier: Topic :: Internet :: WWW/HTTP
Requires-Python: >=3.10
Requires-Dist: cross-inertia>=0.11.0
Requires-Dist: fastapi>=0.100.0
Provides-Extra: api
Requires-Dist: click>=8.0; extra == 'api'
Requires-Dist: griffe>=1.0; extra == 'api'
Provides-Extra: cli
Requires-Dist: click>=8.0; extra == 'cli'
